qri_py/__init__.py
qri_py/ber.py
qri_py-3.0.0.dist-info/METADATA
qri_py-3.0.0.dist-info/RECORD
qri_py-3.0.0.dist-info/WHEEL
qri_py-3.0.0.dist-info/top_level.txt
