Metadata-Version: 2.1
Name: qri-py
Version: 3.0.0
Summary: Qri Python interface
Home-page: https://github.com/Orderry/qri-py
Author: va-dev
Author-email: vadimanikin1@gmail.com
License: UNKNOWN
Platform: UNKNOWN
Requires-Python: >= 3.6
Requires-Dist: pyasn1
